swh/objstorage/replayer/__init__.py
swh/objstorage/replayer/cli.py
swh/objstorage/replayer/py.typed
swh/objstorage/replayer/replay.py
swh/objstorage/replayer/tests/__init__.py
swh/objstorage/replayer/tests/test_cli.py
swh/objstorage/replayer/tests/test_replay.py
swh/objstorage/replayer/tests/test_replay_errors.py
swh/objstorage/replayer/tests/test_statsd.py
swh.objstorage.replayer-2.1.0.dist-info/AUTHORS
swh.objstorage.replayer-2.1.0.dist-info/LICENSE
swh.objstorage.replayer-2.1.0.dist-info/METADATA
swh.objstorage.replayer-2.1.0.dist-info/WHEEL
swh.objstorage.replayer-2.1.0.dist-info/entry_points.txt
swh.objstorage.replayer-2.1.0.dist-info/top_level.txt
swh.objstorage.replayer-2.1.0.dist-info/RECORD
